tfwn
