Metadata-Version: 2.1
Name: tfwn
Version: 1.0.1
Summary: Weight normalization layer for TensorFlow
Home-page: https://github.com/shkarupa-alex/tfwn
Author: Shkarupa Alex
Author-email: shkarupa.alex@gmail.com
License: MIT
Platform: UNKNOWN
Classifier: Development Status :: 5 - Production/Stable
Classifier: Intended Audience :: Developers
Classifier: Intended Audience :: Education
Classifier: Intended Audience :: Science/Research
Classifier: License :: OSI Approved :: MIT License
Classifier: Programming Language :: Python :: 2
Classifier: Programming Language :: Python :: 3
Classifier: Topic :: Scientific/Engineering
Classifier: Topic :: Scientific/Engineering :: Artificial Intelligence
Classifier: Topic :: Software Development
Classifier: Topic :: Software Development :: Libraries
Classifier: Topic :: Software Development :: Libraries :: Python Modules
Provides-Extra: tf_cpu
Provides-Extra: tf_gpu
